git_user_switch/main.py
git_user_switch-1.0.1.dist-info/LICENSE
git_user_switch-1.0.1.dist-info/METADATA
git_user_switch-1.0.1.dist-info/WHEEL
git_user_switch-1.0.1.dist-info/entry_points.txt
git_user_switch-1.0.1.dist-info/RECORD
