Metadata-Version: 2.1
Name: git-user-switch
Version: 1.0.1
Summary: A CLI tool to switch Git user profiles.
Home-page: https://github.com/rosenari/git-user-switch
License: MIT
Author: rosenari
Author-email: rosenari88@gmail.com
Requires-Python: >=3.8,<4.0
Classifier: License :: OSI Approved :: MIT License
Classifier: Programming Language :: Python :: 3
Classifier: Programming Language :: Python :: 3.8
Classifier: Programming Language :: Python :: 3.9
Classifier: Programming Language :: Python :: 3.10
Classifier: Programming Language :: Python :: 3.11
Classifier: Programming Language :: Python :: 3.12
Classifier: Programming Language :: Python :: 3.13
Requires-Dist: pytest (>=8.3.4,<9.0.0)
Project-URL: Repository, https://github.com/rosenari/git-user-switch
